cognitojwt/__init__.py
cognitojwt/constants.py
cognitojwt/exceptions.py
cognitojwt/jwt_async.py
cognitojwt/jwt_sync.py
cognitojwt/token_utils.py
cognitojwt-1.5.0.dist-info/LICENSE
cognitojwt-1.5.0.dist-info/METADATA
cognitojwt-1.5.0.dist-info/WHEEL
cognitojwt-1.5.0.dist-info/top_level.txt
cognitojwt-1.5.0.dist-info/RECORD
