Metadata-Version: 2.1
Name: cognitojwt
Version: 1.5.0
Summary: Decode and verify Amazon Cognito JWT tokens
Home-page: http://github.com/borisrozumnuk/cognitojwt
Author: Boris Rozumniuk
Author-email: borisrozumnuk@gmail.com
License: MIT
Keywords: Amazon Cognito JWT
Platform: Any
Classifier: Development Status :: 4 - Beta
Classifier: Intended Audience :: Developers
Classifier: License :: OSI Approved :: MIT License
Classifier: Programming Language :: Python :: 3.6
Classifier: Programming Language :: Python :: 3.7
Classifier: Operating System :: OS Independent
License-File: LICENSE
Requires-Dist: joserfc
Provides-Extra: async
Requires-Dist: aiofile ; extra == 'async'
Requires-Dist: aiohttp ; extra == 'async'
Requires-Dist: async-lru ; extra == 'async'
Provides-Extra: sync
Requires-Dist: requests ; extra == 'sync'
Provides-Extra: test
Requires-Dist: aiohttp ; extra == 'test'
Requires-Dist: pytest-asyncio ; extra == 'test'
Requires-Dist: attrs ; extra == 'test'
Requires-Dist: pytest ; extra == 'test'
Requires-Dist: async-lru ; extra == 'test'
Requires-Dist: requests ; extra == 'test'
